microapi/__init__.py
microapi/exceptions.py
microapi/http.py
microapi/serializers.py
microapi/tests.py
microapi/views.py
django_microapi-1.2.1.dist-info/LICENSE
django_microapi-1.2.1.dist-info/METADATA
django_microapi-1.2.1.dist-info/WHEEL
django_microapi-1.2.1.dist-info/top_level.txt
django_microapi-1.2.1.dist-info/RECORD
