Metadata-Version: 2.1
Name: django-microapi
Version: 1.2.1
Summary: A tiny library to make writing CBV-based APIs easier in Django.
Author-email: Daniel Lindsley <daniel@toastdriven.com>
License: BSD-3-Clause
Project-URL: Repository, https://github.com/toastdriven/django-microapi.git
Project-URL: Homepage, https://github.com/toastdriven/django-microapi
Project-URL: Issues, https://github.com/toastdriven/django-microapi/issues
Keywords: django,json,api
Classifier: Framework :: Django
Classifier: Programming Language :: Python :: 3
Classifier: License :: OSI Approved :: BSD License
Classifier: Operating System :: OS Independent
Requires-Python: >=3.7
License-File: LICENSE
Requires-Dist: django
